fst_pso-1.9.0.dist-info/licenses/LICENSE
fstpso/__init__.py
fstpso/example.py
fstpso/fftpso.py
fstpso/fstpso.py
fstpso/fstpso_checkpoints.py
fstpso/pso.py
fstpso/surfaces.py
fst_pso-1.9.0.dist-info/METADATA
fst_pso-1.9.0.dist-info/WHEEL
fst_pso-1.9.0.dist-info/top_level.txt
fst_pso-1.9.0.dist-info/RECORD
