Metadata-Version: 2.4
Name: fst-pso
Version: 1.9.0
Summary: Fuzzy Self-Tuning PSO global optimization library
Home-page: https://github.com/aresio/fst-pso
Author: Marco S. Nobile
Author-email: marco.nobile@unive.it
License: LICENSE.txt
Keywords: fuzzy logic,optimization,discrete optimization,continuous optimization,particle swarm optimization,pso,fst-pso,fuzzy self-tuning pso,fuzzy time-travel pso
Classifier: Programming Language :: Python :: 3.7
License-File: LICENSE
Requires-Dist: numpy
Requires-Dist: miniful
Dynamic: author
Dynamic: author-email
Dynamic: classifier
Dynamic: description
Dynamic: home-page
Dynamic: keywords
Dynamic: license
Dynamic: license-file
Dynamic: requires-dist
Dynamic: summary
